wbia_kaggle7/__init__.py
wbia_kaggle7/_plugin.py
wbia_kaggle7/_version.py
wbia_kaggle7/add_bboxes_and_val_fns_and_sample_submission.py
wbia_kaggle7/apply_bboxes.py
wbia_kaggle7/apply_blacklist.py
wbia_kaggle7/arch.py
wbia_kaggle7/export.kaggle7.crc.py
wbia_kaggle7/export.kaggle7.py
wbia_kaggle7/import.valid.py
wbia_kaggle7/losses.py
wbia_kaggle7/server.py
wbia_kaggle7/train_VGG16.py
wbia_kaggle7/train_VGG16_noval.py
wbia_kaggle7/utils.py
wbia_kaggle7-4.0.0.dist-info/LICENSE
wbia_kaggle7-4.0.0.dist-info/METADATA
wbia_kaggle7-4.0.0.dist-info/WHEEL
wbia_kaggle7-4.0.0.dist-info/top_level.txt
wbia_kaggle7-4.0.0.dist-info/RECORD
